{"nodes": [{"id": "e_nest_master_app_ems_wa_line_fuse_starter_v20_0_0_src_app_common_paginate_paginate_component_ts", "label": "paginate.component.ts", "file_type": "code", "source_file": "E:\\Nest\\Master-App\\ems-wa-line\\fuse-starter-v20.0.0\\src\\app\\common\\paginate\\paginate.component.ts", "source_location": "L1"}, {"id": "paginate_paginate_component_paginatecomponent", "label": "PaginateComponent", "file_type": "code", "source_file": "E:\\Nest\\Master-App\\ems-wa-line\\fuse-starter-v20.0.0\\src\\app\\common\\paginate\\paginate.component.ts", "source_location": "L11"}, {"id": "paginate_paginate_component_paginatecomponent_constructor", "label": ".constructor()", "file_type": "code", "source_file": "E:\\Nest\\Master-App\\ems-wa-line\\fuse-starter-v20.0.0\\src\\app\\common\\paginate\\paginate.component.ts", "source_location": "L16"}, {"id": "paginate_paginate_component_paginatecomponent_ngoninit", "label": ".ngOnInit()", "file_type": "code", "source_file": "E:\\Nest\\Master-App\\ems-wa-line\\fuse-starter-v20.0.0\\src\\app\\common\\paginate\\paginate.component.ts", "source_location": "L18"}, {"id": "paginate_paginate_component_paginatecomponent_pages", "label": ".pages()", "file_type": "code", "source_file": "E:\\Nest\\Master-App\\ems-wa-line\\fuse-starter-v20.0.0\\src\\app\\common\\paginate\\paginate.component.ts", "source_location": "L19"}, {"id": "paginate_paginate_component_paginatecomponent_next", "label": ".next()", "file_type": "code", "source_file": "E:\\Nest\\Master-App\\ems-wa-line\\fuse-starter-v20.0.0\\src\\app\\common\\paginate\\paginate.component.ts", "source_location": "L50"}, {"id": "paginate_paginate_component_paginatecomponent_prev", "label": ".prev()", "file_type": "code", "source_file": "E:\\Nest\\Master-App\\ems-wa-line\\fuse-starter-v20.0.0\\src\\app\\common\\paginate\\paginate.component.ts", "source_location": "L59"}, {"id": "paginate_paginate_component_paginatecomponent_gotopage", "label": ".goToPage()", "file_type": "code", "source_file": "E:\\Nest\\Master-App\\ems-wa-line\\fuse-starter-v20.0.0\\src\\app\\common\\paginate\\paginate.component.ts", "source_location": "L68"}, {"id": "paginate_paginate_component_paginatecomponent_ispageenabled", "label": ".isPageEnabled()", "file_type": "code", "source_file": "E:\\Nest\\Master-App\\ems-wa-line\\fuse-starter-v20.0.0\\src\\app\\common\\paginate\\paginate.component.ts", "source_location": "L73"}, {"id": "paginate_paginate_component_paginatecomponent_ispageclickable", "label": ".isPageClickable()", "file_type": "code", "source_file": "E:\\Nest\\Master-App\\ems-wa-line\\fuse-starter-v20.0.0\\src\\app\\common\\paginate\\paginate.component.ts", "source_location": "L77"}, {"id": "paginate_paginate_component_paginatecomponent_setpage", "label": ".setPage()", "file_type": "code", "source_file": "E:\\Nest\\Master-App\\ems-wa-line\\fuse-starter-v20.0.0\\src\\app\\common\\paginate\\paginate.component.ts", "source_location": "L81"}], "edges": [{"source": "e_nest_master_app_ems_wa_line_fuse_starter_v20_0_0_src_app_common_paginate_paginate_component_ts", "target": "common", "relation": "imports_from", "confidence": "EXTRACTED", "source_file": "E:\\Nest\\Master-App\\ems-wa-line\\fuse-starter-v20.0.0\\src\\app\\common\\paginate\\paginate.component.ts", "source_location": "L1", "weight": 1.0}, {"source": "e_nest_master_app_ems_wa_line_fuse_starter_v20_0_0_src_app_common_paginate_paginate_component_ts", "target": "core", "relation": "imports_from", "confidence": "EXTRACTED", "source_file": "E:\\Nest\\Master-App\\ems-wa-line\\fuse-starter-v20.0.0\\src\\app\\common\\paginate\\paginate.component.ts", "source_location": "L2", "weight": 1.0}, {"source": "e_nest_master_app_ems_wa_line_fuse_starter_v20_0_0_src_app_common_paginate_paginate_component_ts", "target": "paginate_paginate_component_paginatecomponent", "relation": "contains", "confidence": "EXTRACTED", "source_file": "E:\\Nest\\Master-App\\ems-wa-line\\fuse-starter-v20.0.0\\src\\app\\common\\paginate\\paginate.component.ts", "source_location": "L11", "weight": 1.0}, {"source": "paginate_paginate_component_paginatecomponent", "target": "paginate_paginate_component_paginatecomponent_constructor", "relation": "method", "confidence": "EXTRACTED", "source_file": "E:\\Nest\\Master-App\\ems-wa-line\\fuse-starter-v20.0.0\\src\\app\\common\\paginate\\paginate.component.ts", "source_location": "L16", "weight": 1.0}, {"source": "paginate_paginate_component_paginatecomponent", "target": "paginate_paginate_component_paginatecomponent_ngoninit", "relation": "method", "confidence": "EXTRACTED", "source_file": "E:\\Nest\\Master-App\\ems-wa-line\\fuse-starter-v20.0.0\\src\\app\\common\\paginate\\paginate.component.ts", "source_location": "L18", "weight": 1.0}, {"source": "paginate_paginate_component_paginatecomponent", "target": "paginate_paginate_component_paginatecomponent_pages", "relation": "method", "confidence": "EXTRACTED", "source_file": "E:\\Nest\\Master-App\\ems-wa-line\\fuse-starter-v20.0.0\\src\\app\\common\\paginate\\paginate.component.ts", "source_location": "L19", "weight": 1.0}, {"source": "paginate_paginate_component_paginatecomponent", "target": "paginate_paginate_component_paginatecomponent_next", "relation": "method", "confidence": "EXTRACTED", "source_file": "E:\\Nest\\Master-App\\ems-wa-line\\fuse-starter-v20.0.0\\src\\app\\common\\paginate\\paginate.component.ts", "source_location": "L50", "weight": 1.0}, {"source": "paginate_paginate_component_paginatecomponent", "target": "paginate_paginate_component_paginatecomponent_prev", "relation": "method", "confidence": "EXTRACTED", "source_file": "E:\\Nest\\Master-App\\ems-wa-line\\fuse-starter-v20.0.0\\src\\app\\common\\paginate\\paginate.component.ts", "source_location": "L59", "weight": 1.0}, {"source": "paginate_paginate_component_paginatecomponent", "target": "paginate_paginate_component_paginatecomponent_gotopage", "relation": "method", "confidence": "EXTRACTED", "source_file": "E:\\Nest\\Master-App\\ems-wa-line\\fuse-starter-v20.0.0\\src\\app\\common\\paginate\\paginate.component.ts", "source_location": "L68", "weight": 1.0}, {"source": "paginate_paginate_component_paginatecomponent", "target": "paginate_paginate_component_paginatecomponent_ispageenabled", "relation": "method", "confidence": "EXTRACTED", "source_file": "E:\\Nest\\Master-App\\ems-wa-line\\fuse-starter-v20.0.0\\src\\app\\common\\paginate\\paginate.component.ts", "source_location": "L73", "weight": 1.0}, {"source": "paginate_paginate_component_paginatecomponent", "target": "paginate_paginate_component_paginatecomponent_ispageclickable", "relation": "method", "confidence": "EXTRACTED", "source_file": "E:\\Nest\\Master-App\\ems-wa-line\\fuse-starter-v20.0.0\\src\\app\\common\\paginate\\paginate.component.ts", "source_location": "L77", "weight": 1.0}, {"source": "paginate_paginate_component_paginatecomponent", "target": "paginate_paginate_component_paginatecomponent_setpage", "relation": "method", "confidence": "EXTRACTED", "source_file": "E:\\Nest\\Master-App\\ems-wa-line\\fuse-starter-v20.0.0\\src\\app\\common\\paginate\\paginate.component.ts", "source_location": "L81", "weight": 1.0}], "raw_calls": [{"caller_nid": "paginate_paginate_component_paginatecomponent_pages", "callee": "push", "source_file": "E:\\Nest\\Master-App\\ems-wa-line\\fuse-starter-v20.0.0\\src\\app\\common\\paginate\\paginate.component.ts", "source_location": "L39"}, {"caller_nid": "paginate_paginate_component_paginatecomponent_pages", "callee": "push", "source_file": "E:\\Nest\\Master-App\\ems-wa-line\\fuse-starter-v20.0.0\\src\\app\\common\\paginate\\paginate.component.ts", "source_location": "L42"}, {"caller_nid": "paginate_paginate_component_paginatecomponent_pages", "callee": "push", "source_file": "E:\\Nest\\Master-App\\ems-wa-line\\fuse-starter-v20.0.0\\src\\app\\common\\paginate\\paginate.component.ts", "source_location": "L45"}, {"caller_nid": "paginate_paginate_component_paginatecomponent_next", "callee": "emit", "source_file": "E:\\Nest\\Master-App\\ems-wa-line\\fuse-starter-v20.0.0\\src\\app\\common\\paginate\\paginate.component.ts", "source_location": "L56"}, {"caller_nid": "paginate_paginate_component_paginatecomponent_prev", "callee": "emit", "source_file": "E:\\Nest\\Master-App\\ems-wa-line\\fuse-starter-v20.0.0\\src\\app\\common\\paginate\\paginate.component.ts", "source_location": "L65"}, {"caller_nid": "paginate_paginate_component_paginatecomponent_gotopage", "callee": "emit", "source_file": "E:\\Nest\\Master-App\\ems-wa-line\\fuse-starter-v20.0.0\\src\\app\\common\\paginate\\paginate.component.ts", "source_location": "L70"}, {"caller_nid": "paginate_paginate_component_paginatecomponent_setpage", "callee": "emit", "source_file": "E:\\Nest\\Master-App\\ems-wa-line\\fuse-starter-v20.0.0\\src\\app\\common\\paginate\\paginate.component.ts", "source_location": "L84"}]}