{"nodes": [{"id": "e_nest_master_app_ems_wa_line_be_src_datalist_entities_datalist_entity_ts", "label": "datalist.entity.ts", "file_type": "code", "source_file": "E:\\Nest\\Master-App\\ems-wa-line\\be\\src\\datalist\\entities\\datalist.entity.ts", "source_location": "L1"}, {"id": "entities_datalist_entity_datalist", "label": "Datalist", "file_type": "code", "source_file": "E:\\Nest\\Master-App\\ems-wa-line\\be\\src\\datalist\\entities\\datalist.entity.ts", "source_location": "L4"}], "edges": [{"source": "e_nest_master_app_ems_wa_line_be_src_datalist_entities_datalist_entity_ts", "target": "typeorm", "relation": "imports_from", "confidence": "EXTRACTED", "source_file": "E:\\Nest\\Master-App\\ems-wa-line\\be\\src\\datalist\\entities\\datalist.entity.ts", "source_location": "L1", "weight": 1.0}, {"source": "e_nest_master_app_ems_wa_line_be_src_datalist_entities_datalist_entity_ts", "target": "entities_datalist_entity_datalist", "relation": "contains", "confidence": "EXTRACTED", "source_file": "E:\\Nest\\Master-App\\ems-wa-line\\be\\src\\datalist\\entities\\datalist.entity.ts", "source_location": "L4", "weight": 1.0}], "raw_calls": []}