{"nodes": [{"id": "e_nest_master_app_ems_wa_line_frontend_ems_src_fuse_version_version_ts", "label": "version.ts", "file_type": "code", "source_file": "E:\\Nest\\Master-App\\ems-wa-line\\frontend-ems\\src\\@fuse\\version\\version.ts", "source_location": "L1"}, {"id": "version_version_version", "label": "Version", "file_type": "code", "source_file": "E:\\Nest\\Master-App\\ems-wa-line\\frontend-ems\\src\\@fuse\\version\\version.ts", "source_location": "L4"}, {"id": "version_version_version_constructor", "label": ".constructor()", "file_type": "code", "source_file": "E:\\Nest\\Master-App\\ems-wa-line\\frontend-ems\\src\\@fuse\\version\\version.ts", "source_location": "L13"}], "edges": [{"source": "e_nest_master_app_ems_wa_line_frontend_ems_src_fuse_version_version_ts", "target": "version_version_version", "relation": "contains", "confidence": "EXTRACTED", "source_file": "E:\\Nest\\Master-App\\ems-wa-line\\frontend-ems\\src\\@fuse\\version\\version.ts", "source_location": "L4", "weight": 1.0}, {"source": "version_version_version", "target": "version_version_version_constructor", "relation": "method", "confidence": "EXTRACTED", "source_file": "E:\\Nest\\Master-App\\ems-wa-line\\frontend-ems\\src\\@fuse\\version\\version.ts", "source_location": "L13", "weight": 1.0}], "raw_calls": [{"caller_nid": "version_version_version_constructor", "callee": "split", "source_file": "E:\\Nest\\Master-App\\ems-wa-line\\frontend-ems\\src\\@fuse\\version\\version.ts", "source_location": "L15"}, {"caller_nid": "version_version_version_constructor", "callee": "split", "source_file": "E:\\Nest\\Master-App\\ems-wa-line\\frontend-ems\\src\\@fuse\\version\\version.ts", "source_location": "L16"}, {"caller_nid": "version_version_version_constructor", "callee": "join", "source_file": "E:\\Nest\\Master-App\\ems-wa-line\\frontend-ems\\src\\@fuse\\version\\version.ts", "source_location": "L17"}, {"caller_nid": "version_version_version_constructor", "callee": "slice", "source_file": "E:\\Nest\\Master-App\\ems-wa-line\\frontend-ems\\src\\@fuse\\version\\version.ts", "source_location": "L17"}, {"caller_nid": "version_version_version_constructor", "callee": "split", "source_file": "E:\\Nest\\Master-App\\ems-wa-line\\frontend-ems\\src\\@fuse\\version\\version.ts", "source_location": "L17"}]}